pytest_flask_sqlalchemy_transactions-1.0.2.dist-info/METADATA
pytest_flask_sqlalchemy_transactions-1.0.2.dist-info/RECORD
pytest_flask_sqlalchemy_transactions-1.0.2.dist-info/WHEEL
pytest_flask_sqlalchemy_transactions-1.0.2.dist-info/entry_points.txt
pytest_flask_sqlalchemy_transactions-1.0.2.dist-info/top_level.txt
transactions/__init__.py
transactions/fixtures.py
transactions/plugin.py
